[{"type":"rotation","time":1617726979629,"XR":-0,"YR":0,"ZR":0},{"type":"rotation","time":1617726979645,"XR":-0,"YR":0,"ZR":0},{"type":"rotation","time":1617726979666,"XR":-0,"YR":0,"ZR":0},{"type":"rotation","time":1617726979686,"XR":-0,"YR":0,"ZR":0},{"type":"rotation","time":1617726979706,"XR":-0,"YR":0,"ZR":0},{"type":"rotation","time":1617726979726,"XR":0,"YR":0,"ZR":0},{"type":"rotation","time":1617726979746,"XR":0,"YR":0,"ZR":0},{"type":"rotation","time":1617726979766,"XR":0,"YR":0,"ZR":0},{"type":"rotation","time":1617726979786,"XR":0,"YR":0,"ZR":0},{"type":"rotation","time":1617726979806,"XR":0,"YR":0,"ZR":0},{"type":"rotation","time":1617726979937,"XR":0,"YR":0,"ZR":0},{"type":"rotation","time":1617726979937,"XR":0,"YR":0,"ZR":0},{"type":"rotation","time":1617726979937,"XR":0,"YR":0,"ZR":0},{"type":"rotation","time":1617726979937,"XR":0,"YR":0,"ZR":0},{"type":"rotation","time":1617726979937,"XR":0,"YR":0,"ZR":0},{"type":"rotation","time":1617726979937,"XR":0,"YR":0,"ZR":0},{"type":"rotation","time":1617726979946,"XR":0,"YR":0,"ZR":0},{"type":"rotation","time":1617726979965,"XR":0,"YR":0,"ZR":0},{"type":"rotation","time":1617726979986,"XR":0,"YR":0,"ZR":0},{"type":"rotation","time":1617726980006,"XR":0,"YR":0,"ZR":0},{"type":"rotation","time":1617726980026,"XR":0,"YR":0,"ZR":0},{"type":"rotation","time":1617726980047,"XR":0,"YR":0,"ZR":0},{"type":"rotation","time":1617726980065,"XR":0,"YR":0,"ZR":0},{"type":"rotation","time":1617726980086,"XR":0,"YR":0,"ZR":0},{"type":"rotation","time":1617726980106,"XR":0,"YR":0,"ZR":0},{"type":"rotation","time":1617726980126,"XR":0,"YR":0,"ZR":0},{"type":"rotation","time":1617726980148,"XR":0,"YR":0,"ZR":0},{"type":"rotation","time":1617726980165,"XR":0,"YR":0,"ZR":0},{"type":"rotation","time":1617726980185,"XR":0,"YR":0,"ZR":0},{"type":"rotation","time":1617726980205,"XR":0,"YR":0,"ZR":0}]